Workbook

Sheet Instructions
A1: rFLA300 — Chapter 11: Financial Models
B2: Asset Depreciation — SLN, DB, and DDB
A4: 📋 File Contents
B5: Sheet | C5: Purpose
B6: Instructions | C6: Overview of file purpose and color key
B7: Depreciation_Methods | C7: Compare SLN, DB, and DDB for the same asset
B8: DDB_Schedule | C8: Year-by-year DDB depreciation table
A11: 🎨 Color Key
B12: Sample | C12: Input / Assumption cells — enter your values here
B13: Sample | C13: Result cells — calculated by Excel formulas
B14: Sample | C14: Labels — descriptions of each row
B15: Sample | C15: Section headers

Sheet Depreciation_Methods
A1: Depreciation Methods — SLN, DB, and DDB
B2: Scenario: A manufacturing company buys equipment for $50,000 with a 5-year life and $5,000 salvage value.
A4: 📥 Asset Details
B5: Cost (Original Value) | C5: 50000
B6: Salvage Value | C6: 5000
B7: Useful Life (Years) | C7: 5
B8: Period to Inspect | C8: 1
A10: 📊 Method 1: Straight-Line Depreciation [SLN]
B11: =SLN(cost, salvage, life) → Same amount every year
B12: Annual Depreciation (every year) | C12: =SLN(C5,C6,C7)
B13: Total Depreciation over Life | C13: =C12*C7
B14: Book Value at End of Life | C14: =C5-C13
A16: 📊 Method 2: Declining Balance [DB]
B17: =DB(cost, salvage, life, period, [month]) → Higher depreciation in early years
B18: Depreciation in Period (from cell C8) | C18: =DB(C5,C6,C7,C8)
B19: Period 1 (first year) | C19: =DB(C5,C6,C7,1)
B20: Period 5 (last year) | C20: =DB(C5,C6,C7,5)
B21: DB Fixed Rate Used | C21: =1-(C6/C5)^(1/C7)
A23: 📊 Method 3: Double Declining Balance [DDB]
B24: =DDB(cost, salvage, life, period, [factor]) → Fastest depreciation; factor=2 by default
B25: Depreciation in Period (from cell C8) | C25: =DDB(C5,C6,C7,C8,2)
B26: Period 1 (first year) | C26: =DDB(C5,C6,C7,1,2)
B27: Period 5 (last year) | C27: =DDB(C5,C6,C7,5,2)
A29: 📋 Quick Method Comparison
B30: Method | C30: Year 1 | D30: Year 5 | E30: Best Used When
B31: SLN | C31: =SLN($C$5,$C$6,$C$7) | D31: =SLN($C$5,$C$6,$C$7) | E31: Asset wears evenly; simple accounting
B32: DB | C32: =DB($C$5,$C$6,$C$7,1) | D32: =DB($C$5,$C$6,$C$7,5) | E32: Asset loses more value early; matches IRS tables
B33: DDB | C33: =DDB($C$5,$C$6,$C$7,1,2) | D33: =DDB($C$5,$C$6,$C$7,5,2) | E33: Maximum early deduction; tech assets
A35: ✏️ Practice Tasks
B36: 1. Change Period to 3. Compare the depreciation across all three methods.
B37: 2. Change salvage value to $0. How does DDB behave in the last period?
B38: 3. Change useful life to 10 years. Which method gives the biggest deduction in year 1?
B39: 4. Use DDB with factor=1.5 (150% declining balance). Compare to factor=2.

Sheet DDB_Schedule
A1: Year-by-Year Depreciation Comparison Schedule
B2: This table shows all three methods side by side for every year of the asset's life. (Linked to Depreciation_Methods inputs.)
A4: 📋 Annual Depreciation Table
B5: Year | C5: SLN | D5: DB | E5: DDB | F5: SLN Book Value | G5: DB Book Value | H5: DDB Book Value
B6: 1 | C6: =SLN(Depreciation_Methods!$C$5,Depreciation_Methods!$C$6,Depreciation_Methods!$C$7) | D6: =DB(Depreciation_Methods!$C$5,Depreciation_Methods!$C$6,Depreciation_Methods!$C$7,1) | E6: =DDB(Depreciation_Methods!$C$5,Depreciation_Methods!$C$6,Depreciation_Methods!$C$7,1,2) | F6: =Depreciation_Methods!$C$5-C6 | G6: =Depreciation_Methods!$C$5-D6 | H6: =Depreciation_Methods!$C$5-E6
B7: 2 | C7: =SLN(Depreciation_Methods!$C$5,Depreciation_Methods!$C$6,Depreciation_Methods!$C$7) | D7: =DB(Depreciation_Methods!$C$5,Depreciation_Methods!$C$6,Depreciation_Methods!$C$7,2) | E7: =DDB(Depreciation_Methods!$C$5,Depreciation_Methods!$C$6,Depreciation_Methods!$C$7,2,2) | F7: =F6-C7 | G7: =G6-D7 | H7: =H6-E7
B8: 3 | C8: =SLN(Depreciation_Methods!$C$5,Depreciation_Methods!$C$6,Depreciation_Methods!$C$7) | D8: =DB(Depreciation_Methods!$C$5,Depreciation_Methods!$C$6,Depreciation_Methods!$C$7,3) | E8: =DDB(Depreciation_Methods!$C$5,Depreciation_Methods!$C$6,Depreciation_Methods!$C$7,3,2) | F8: =F7-C8 | G8: =G7-D8 | H8: =H7-E8
B9: 4 | C9: =SLN(Depreciation_Methods!$C$5,Depreciation_Methods!$C$6,Depreciation_Methods!$C$7) | D9: =DB(Depreciation_Methods!$C$5,Depreciation_Methods!$C$6,Depreciation_Methods!$C$7,4) | E9: =DDB(Depreciation_Methods!$C$5,Depreciation_Methods!$C$6,Depreciation_Methods!$C$7,4,2) | F9: =F8-C9 | G9: =G8-D9 | H9: =H8-E9
B10: 5 | C10: =SLN(Depreciation_Methods!$C$5,Depreciation_Methods!$C$6,Depreciation_Methods!$C$7) | D10: =DB(Depreciation_Methods!$C$5,Depreciation_Methods!$C$6,Depreciation_Methods!$C$7,5) | E10: =DDB(Depreciation_Methods!$C$5,Depreciation_Methods!$C$6,Depreciation_Methods!$C$7,5,2) | F10: =F9-C10 | G10: =G9-D10 | H10: =H9-E10
B12: Total | C12: =SUM(C6:C10) | D12: =SUM(D6:D10) | E12: =SUM(E6:E10)
A14: 💡 Key Insight
B15: • All three methods depreciate the same total amount (cost − salvage) over the asset's life.
B16: • They ONLY differ in TIMING — when the deductions occur.
B17: • Faster depreciation (DDB) = bigger deductions early = lower taxes now = better cash flow today.
B18: • SLN gives predictable, stable expense. DB/DDB match accelerated wear on technology and vehicles.
