Workbook

Sheet Historical_Data
A1: Historical Sales Data — 36 Months (Jan 2022 – Dec 2024)
A2: This dataset contains 36 months of retail sales with a clear upward trend and seasonal pattern. We will use this data to build forecasts with FORECAST.LINEAR and FORECAST.ETS, and compare their accuracy.
A4: Period # | B4: Date | C4: Revenue ($K) | D4: Units Sold | E4: Online Orders | F4: Store Traffic | G4: Notes
A5: 1 | B5: Jan 2022 | C5: 55.9 | D5: 791 | E5: 308 | F5: 4721
A6: 2 | B6: Feb 2022 | C6: 52.7 | D6: 752 | E6: 293 | F6: 4405
A7: 3 | B7: Mar 2022 | C7: 60.8 | D7: 895 | E7: 327 | F7: 5219
A8: 4 | B8: Apr 2022 | C8: 63.6 | D8: 903 | E8: 330 | F8: 5361
A9: 5 | B9: May 2022 | C9: 68.1 | D9: 1005 | E9: 366 | F9: 5831
A10: 6 | B10: Jun 2022 | C10: 70.8 | D10: 1040 | E10: 393 | F10: 5974
A11: 7 | B11: Jul 2022 | C11: 76.4 | D11: 1104 | E11: 429 | F11: 6395
A12: 8 | B12: Aug 2022 | C12: 77.4 | D12: 1112 | E12: 429 | F12: 6587
A13: 9 | B13: Sep 2022 | C13: 70.4 | D13: 1009 | E13: 374 | F13: 6079
A14: 10 | B14: Oct 2022 | C14: 69.8 | D14: 997 | E14: 375 | F14: 5857
A15: 11 | B15: Nov 2022 | C15: 80.8 | D15: 1173 | E15: 449 | F15: 6835
A16: 12 | B16: Dec 2022 | C16: 100.9 | D16: 1472 | E16: 561 | F16: 8507
... A26: 22 | B26: Oct 2023 | C26: 79.1 | D26: 1166 | E26: 450 | F26: 6765
A27: 23 | B27: Nov 2023 | C27: 90.6 | D27: 1313 | E27: 509 | F27: 7796 | G27: Black Friday record
A28: 24 | B28: Dec 2023 | C28: 113.3 | D28: 1636 | E28: 632 | F28: 9538 | G28: Holiday surge
A29: 25 | B29: Jan 2024 | C29: 72.7 | D29: 1059 | E29: 395 | F29: 6095
A30: 26 | B30: Feb 2024 | C30: 67.8 | D30: 999 | E30: 392 | F30: 5846
A31: 27 | B31: Mar 2024 | C31: 75.8 | D31: 1110 | E31: 418 | F31: 6507
A32: 28 | B32: Apr 2024 | C32: 81.6 | D32: 1179 | E32: 437 | F32: 6898
A33: 29 | B33: May 2024 | C33: 89.8 | D33: 1316 | E33: 493 | F33: 7724
A34: 30 | B34: Jun 2024 | C34: 92.4 | D34: 1356 | E34: 512 | F34: 7846
A35: 31 | B35: Jul 2024 | C35: 95.8 | D35: 1377 | E35: 524 | F35: 8169
A36: 32 | B36: Aug 2024 | C36: 94.3 | D36: 1350 | E36: 525 | F36: 7943
A37: 33 | B37: Sep 2024 | C37: 88.2 | D37: 1268 | E37: 491 | F37: 7571
A38: 34 | B38: Oct 2024 | C38: 88.5 | D38: 1267 | E38: 478 | F38: 7519
A39: 35 | B39: Nov 2024 | C39: 103 | D39: 1502 | E39: 571 | F39: 8719 | G39: Promo campaign
A40: 36 | B40: Dec 2024 | C40: 127 | D40: 1821 | E40: 697 | F40: 10879 | G40: All-time high

Sheet FORECAST_Functions
A1: Forecasting Future Values — FORECAST.LINEAR and FORECAST.ETS (Objective 9)
A2: FORECAST.LINEAR fits a straight-line trend (good for steady growth). FORECAST.ETS uses Exponential Triple Smoothing — it detects and projects TREND + SEASONALITY automatically, making it more accurate for data with regular seasonal patterns. Both functions extend your historical data into the future.
A4: Period | B4: Date | C4: Actual Revenue ($K) | D4: LINEAR Forecast | E4: ETS Forecast | F4: Forecast Error (ETS) | G4: Notes
A5: 1 | B5: Jan 2022 | C5: 55.9 | D5: =FORECAST(A5,Historical_Data!$C$5:$C$40,Historical_Data!$A$5:$A$40) | E5: =_xlfn.FORECAST.ETS(A5,Historical_Data!$C$5:$C$40,Historical_Data!$A$5:$A$40,12) | F5: =C5-E5 | G5: Historical
A6: 2 | B6: Feb 2022 | C6: 52.7 | D6: =FORECAST(A6,Historical_Data!$C$5:$C$40,Historical_Data!$A$5:$A$40) | E6: =_xlfn.FORECAST.ETS(A6,Historical_Data!$C$5:$C$40,Historical_Data!$A$5:$A$40,12) | F6: =C6-E6 | G6: Historical
A7: 3 | B7: Mar 2022 | C7: 60.8 | D7: =FORECAST(A7,Historical_Data!$C$5:$C$40,Historical_Data!$A$5:$A$40) | E7: =_xlfn.FORECAST.ETS(A7,Historical_Data!$C$5:$C$40,Historical_Data!$A$5:$A$40,12) | F7: =C7-E7 | G7: Historical
A8: 4 | B8: Apr 2022 | C8: 63.6 | D8: =FORECAST(A8,Historical_Data!$C$5:$C$40,Historical_Data!$A$5:$A$40) | E8: =_xlfn.FORECAST.ETS(A8,Historical_Data!$C$5:$C$40,Historical_Data!$A$5:$A$40,12) | F8: =C8-E8 | G8: Historical
A9: 5 | B9: May 2022 | C9: 68.1 | D9: =FORECAST(A9,Historical_Data!$C$5:$C$40,Historical_Data!$A$5:$A$40) | E9: =_xlfn.FORECAST.ETS(A9,Historical_Data!$C$5:$C$40,Historical_Data!$A$5:$A$40,12) | F9: =C9-E9 | G9: Historical
A10: 6 | B10: Jun 2022 | C10: 70.8 | D10: =FORECAST(A10,Historical_Data!$C$5:$C$40,Historical_Data!$A$5:$A$40) | E10: =_xlfn.FORECAST.ETS(A10,Historical_Data!$C$5:$C$40,Historical_Data!$A$5:$A$40,12) | F10: =C10-E10 | G10: Historical
A11: 7 | B11: Jul 2022 | C11: 76.4 | D11: =FORECAST(A11,Historical_Data!$C$5:$C$40,Historical_Data!$A$5:$A$40) | E11: =_xlfn.FORECAST.ETS(A11,Historical_Data!$C$5:$C$40,Historical_Data!$A$5:$A$40,12) | F11: =C11-E11 | G11: Historical
A12: 8 | B12: Aug 2022 | C12: 77.4 | D12: =FORECAST(A12,Historical_Data!$C$5:$C$40,Historical_Data!$A$5:$A$40) | E12: =_xlfn.FORECAST.ETS(A12,Historical_Data!$C$5:$C$40,Historical_Data!$A$5:$A$40,12) | F12: =C12-E12 | G12: Historical
A13: 9 | B13: Sep 2022 | C13: 70.4 | D13: =FORECAST(A13,Historical_Data!$C$5:$C$40,Historical_Data!$A$5:$A$40) | E13: =_xlfn.FORECAST.ETS(A13,Historical_Data!$C$5:$C$40,Historical_Data!$A$5:$A$40,12) | F13: =C13-E13 | G13: Historical
A14: 10 | B14: Oct 2022 | C14: 69.8 | D14: =FORECAST(A14,Historical_Data!$C$5:$C$40,Historical_Data!$A$5:$A$40) | E14: =_xlfn.FORECAST.ETS(A14,Historical_Data!$C$5:$C$40,Historical_Data!$A$5:$A$40,12) | F14: =C14-E14 | G14: Historical
A15: 11 | B15: Nov 2022 | C15: 80.8 | D15: =FORECAST(A15,Historical_Data!$C$5:$C$40,Historical_Data!$A$5:$A$40) | E15: =_xlfn.FORECAST.ETS(A15,Historical_Data!$C$5:$C$40,Historical_Data!$A$5:$A$40,12) | F15: =C15-E15 | G15: Historical
A16: 12 | B16: Dec 2022 | C16: 100.9 | D16: =FORECAST(A16,Historical_Data!$C$5:$C$40,Historical_Data!$A$5:$A$40) | E16: =_xlfn.FORECAST.ETS(A16,Historical_Data!$C$5:$C$40,Historical_Data!$A$5:$A$40,12) | F16: =C16-E16 | G16: Historical
... A40: 36 | B40: Dec 2024 | C40: 127 | D40: =FORECAST(A40,Historical_Data!$C$5:$C$40,Historical_Data!$A$5:$A$40) | E40: =_xlfn.FORECAST.ETS(A40,Historical_Data!$C$5:$C$40,Historical_Data!$A$5:$A$40,12) | F40: =C40-E40 | G40: Historical
A41: 37 | B41: Jan 2025 | C41: — | D41: =FORECAST(A41,Historical_Data!$C$5:$C$40,Historical_Data!$A$5:$A$40) | E41: =_xlfn.FORECAST.ETS(A41,Historical_Data!$C$5:$C$40,Historical_Data!$A$5:$A$40,12) | G41: FORECAST ← new
A42: 38 | B42: Feb 2025 | C42: — | D42: =FORECAST(A42,Historical_Data!$C$5:$C$40,Historical_Data!$A$5:$A$40) | E42: =_xlfn.FORECAST.ETS(A42,Historical_Data!$C$5:$C$40,Historical_Data!$A$5:$A$40,12) | G42: FORECAST ← new
A43: 39 | B43: Mar 2025 | C43: — | D43: =FORECAST(A43,Historical_Data!$C$5:$C$40,Historical_Data!$A$5:$A$40) | E43: =_xlfn.FORECAST.ETS(A43,Historical_Data!$C$5:$C$40,Historical_Data!$A$5:$A$40,12) | G43: FORECAST ← new
A44: 40 | B44: Apr 2025 | C44: — | D44: =FORECAST(A44,Historical_Data!$C$5:$C$40,Historical_Data!$A$5:$A$40) | E44: =_xlfn.FORECAST.ETS(A44,Historical_Data!$C$5:$C$40,Historical_Data!$A$5:$A$40,12) | G44: FORECAST ← new
A45: 41 | B45: May 2025 | C45: — | D45: =FORECAST(A45,Historical_Data!$C$5:$C$40,Historical_Data!$A$5:$A$40) | E45: =_xlfn.FORECAST.ETS(A45,Historical_Data!$C$5:$C$40,Historical_Data!$A$5:$A$40,12) | G45: FORECAST ← new
A46: 42 | B46: Jun 2025 | C46: — | D46: =FORECAST(A46,Historical_Data!$C$5:$C$40,Historical_Data!$A$5:$A$40) | E46: =_xlfn.FORECAST.ETS(A46,Historical_Data!$C$5:$C$40,Historical_Data!$A$5:$A$40,12) | G46: FORECAST ← new
A47: 43 | B47: Jul 2025 | C47: — | D47: =FORECAST(A47,Historical_Data!$C$5:$C$40,Historical_Data!$A$5:$A$40) | E47: =_xlfn.FORECAST.ETS(A47,Historical_Data!$C$5:$C$40,Historical_Data!$A$5:$A$40,12) | G47: FORECAST ← new
A48: 44 | B48: Aug 2025 | C48: — | D48: =FORECAST(A48,Historical_Data!$C$5:$C$40,Historical_Data!$A$5:$A$40) | E48: =_xlfn.FORECAST.ETS(A48,Historical_Data!$C$5:$C$40,Historical_Data!$A$5:$A$40,12) | G48: FORECAST ← new
A49: 45 | B49: Sep 2025 | C49: — | D49: =FORECAST(A49,Historical_Data!$C$5:$C$40,Historical_Data!$A$5:$A$40) | E49: =_xlfn.FORECAST.ETS(A49,Historical_Data!$C$5:$C$40,Historical_Data!$A$5:$A$40,12) | G49: FORECAST ← new
A50: 46 | B50: Oct 2025 | C50: — | D50: =FORECAST(A50,Historical_Data!$C$5:$C$40,Historical_Data!$A$5:$A$40) | E50: =_xlfn.FORECAST.ETS(A50,Historical_Data!$C$5:$C$40,Historical_Data!$A$5:$A$40,12) | G50: FORECAST ← new
A51: 47 | B51: Nov 2025 | C51: — | D51: =FORECAST(A51,Historical_Data!$C$5:$C$40,Historical_Data!$A$5:$A$40) | E51: =_xlfn.FORECAST.ETS(A51,Historical_Data!$C$5:$C$40,Historical_Data!$A$5:$A$40,12) | G51: FORECAST ← new
A52: 48 | B52: Dec 2025 | C52: — | D52: =FORECAST(A52,Historical_Data!$C$5:$C$40,Historical_Data!$A$5:$A$40) | E52: =_xlfn.FORECAST.ETS(A52,Historical_Data!$C$5:$C$40,Historical_Data!$A$5:$A$40,12) | G52: FORECAST ← new
A54: Forecast Accuracy — Mean Absolute Error (MAE)
A55: Model | B55: Formula | C55: MAE ($K) | D55: Interpretation
A56: FORECAST.LINEAR | B56: '=AVERAGE(ABS(C5:C40-D5:D40)) | C56: =AVERAGE(ABS(C5:C40-D5:D40)) | D56: Average error of the straight-line trend fit.
A57: FORECAST.ETS | B57: '=AVERAGE(ABS(F5:F40)) | C57: =AVERAGE(ABS(F5:F40)) | D57: Average error of the trend+seasonality model. Usually lower.

Sheet Forecasting_Concepts
A1: Forecasting Concepts and Best Practices (Objective 9)
A3: Concept | B3: What It Means | C3: Excel Implementation | D3: When to Use | E3: Business Example
A4: Trend | B4: The long-term upward or downward direction in the data. | C4: FORECAST.LINEAR — fits a straight line through historical data | D4: Data has clear upward/downward movement, no strong seasonality | E4: Annual revenue growing steadily at 8% per year
A5: Seasonality | B5: Regular, repeating patterns within a fixed cycle (usually 12 months). | C5: FORECAST.ETS with seasonality=12 — automatically detects and projects seasonal waves | D5: Data repeats similar patterns every year (retail, tourism, agriculture) | E5: High sales in Dec, low in Feb every year
A6: FORECAST.LINEAR | B6: Extends historical data using linear regression (Y = mx + b). | C6: =FORECAST(x, known_ys, known_xs) x = future period number | D6: Simple trend with no strong seasonality | E6: Projecting unit sales 6 months ahead when trend is stable
A7: FORECAST.ETS | B7: Exponential Triple Smoothing — models level + trend + seasonality. | C7: =FORECAST.ETS(target_date, values, timeline, seasonality) Seasonality: 12 for monthly, 4 for quarterly | D7: Data with BOTH trend AND seasonal variation | E7: Monthly retail revenue with holiday spikes
A8: FORECAST.ETS.CONFINT | B8: Generates a confidence interval around the ETS forecast. | C8: =FORECAST.ETS.CONFINT(target, values, timeline, confidence, seasonality) confidence: 0.95 = 95% interval | D8: When you need to communicate forecast uncertainty | E8: Report best case / worst case scenarios to leadership
A9: Moving Average | B9: Smooths out noise by averaging the last N periods. | C9: No built-in function — calculate with =AVERAGE(last N rows) ToolPak: Moving Average tool | D9: Data is noisy; want to see underlying trend | E9: Average last 3 months of sales to smooth week-to-week variation
A10: Holdout Validation | B10: Using part of historical data to test forecast accuracy. | C10: Reserve last 6–12 rows as a 'test set'; train on earlier rows; compare predictions to actuals | D10: Always — before trusting any forecast model | E10: Train on months 1-30, forecast months 31-36, measure error
A11: Mean Absolute Error (MAE) | B11: Average of |actual - predicted| — lower is better. | C11: =AVERAGE(ABS(actuals_range - forecasts_range)) where actuals and forecasts are cell ranges | D11: Evaluating and comparing forecast models | E11: FORECAST.ETS MAE=$3.2K vs LINEAR MAE=$4.8K → ETS wins
A12: Forecast Horizon | B12: How far into the future you are projecting. | C12: Any future period number in FORECAST functions | D12: Planning cycle length | E12: Quarterly planning = 3-month horizon; annual budget = 12-month horizon
A13: Extrapolation Risk | B13: Forecasts degrade in accuracy the further you project. | C13: Compare 1-month vs 12-month ahead forecast errors | D13: Always — be more cautious about longer forecasts | E13: Do not blindly project 5 years using 2 years of data
A15: ✏️ Practice Challenge: Using the FORECAST_Functions sheet, which model (LINEAR or ETS) has a lower MAE? Why do you think one outperforms the other on this dataset? Change the season argument in FORECAST.ETS from 12 to 1 — what happens to the forecast?
